{
  "last_scan": "2026-06-19T10:24:45Z",
  "status": "success",
  "total_founded": 7,
  "cumulative": 4428,
  "cpm": 0,
  "by_provider": {
    "aws_secret": 3,
    "discord": 1,
    "twilio": 3
  },
  "by_source": {
    "gist": 7
  },
  "by_status": {
    "unverified": 7
  },
  "recent_masked": [
    {
      "provider": "AWS Secret Key",
      "masked": "6ab2a...5f7b",
      "status": "unverified",
      "source": "gist"
    },
    {
      "provider": "AWS Secret Key",
      "masked": "Qb0LZ...CQkM",
      "status": "unverified",
      "source": "gist"
    },
    {
      "provider": "AWS Secret Key",
      "masked": "h45fp...RjoC",
      "status": "unverified",
      "source": "gist"
    },
    {
      "provider": "Discord Bot",
      "masked": "NOOJf...48PG",
      "status": "unverified",
      "source": "gist"
    },
    {
      "provider": "Twilio",
      "masked": "ACSk2...wQ2e",
      "status": "unverified",
      "source": "gist"
    },
    {
      "provider": "Twilio",
      "masked": "ACFvB...oaQb",
      "status": "unverified",
      "source": "gist"
    },
    {
      "provider": "Twilio",
      "masked": "ACSx8...5sLC",
      "status": "unverified",
      "source": "gist"
    }
  ]
}