{
  "last_scan": "2026-06-19T09:50:41Z",
  "status": "success",
  "total_founded": 8,
  "cumulative": 4296,
  "cpm": 0,
  "by_provider": {
    "aws_secret": 7,
    "discord": 1
  },
  "by_source": {
    "gist": 8
  },
  "by_status": {
    "unverified": 8
  },
  "recent_masked": [
    {
      "provider": "AWS Secret Key",
      "masked": "pbk=w...Eh1R",
      "status": "unverified",
      "source": "gist"
    },
    {
      "provider": "AWS Secret Key",
      "masked": "524d1...4ded",
      "status": "unverified",
      "source": "gist"
    },
    {
      "provider": "AWS Secret Key",
      "masked": "Lv0XA...0EBs",
      "status": "unverified",
      "source": "gist"
    },
    {
      "provider": "AWS Secret Key",
      "masked": "f3e8b...e31b",
      "status": "unverified",
      "source": "gist"
    },
    {
      "provider": "AWS Secret Key",
      "masked": "b6833...b156",
      "status": "unverified",
      "source": "gist"
    },
    {
      "provider": "AWS Secret Key",
      "masked": "117e4...4d44",
      "status": "unverified",
      "source": "gist"
    },
    {
      "provider": "AWS Secret Key",
      "masked": "03886...ac0f",
      "status": "unverified",
      "source": "gist"
    },
    {
      "provider": "Discord Bot",
      "masked": "NXIoE...Xbew",
      "status": "unverified",
      "source": "gist"
    }
  ]
}